dbt_core_interface/__init__.py
dbt_core_interface/client.py
dbt_core_interface/container.py
dbt_core_interface/dbt_templater/LICENSE.md
dbt_core_interface/dbt_templater/__init__.py
dbt_core_interface/dbt_templater/templater.py
dbt_core_interface/project.py
dbt_core_interface/server.py
dbt_core_interface/watcher.py
dbt_core_interface-1.1.5.dist-info/WHEEL
dbt_core_interface-1.1.5.dist-info/entry_points.txt
dbt_core_interface-1.1.5.dist-info/METADATA
dbt_core_interface-1.1.5.dist-info/RECORD
