Metadata-Version: 2.3
Name: dbt-core-interface
Version: 1.1.5
Summary: Dbt Core Interface
Keywords: dbt,sqlfluff
Author: Alex Butler
Author-email: Alex Butler <butler.alex2010@gmail.com>
License: MIT
Classifier: Development Status :: 4 - Beta
Requires-Dist: dbt-core>=1.8.0,<2.0.0
Requires-Dist: dbt-adapters>=1.3.2
Requires-Dist: rich>10.0
Requires-Dist: typing-extensions ; python_full_version < '3.10'
Requires-Dist: dbt-duckdb ; extra == 'dev'
Requires-Dist: ruff~=0.12.0 ; extra == 'dev'
Requires-Dist: coverage[toml]>=6.2,<7 ; extra == 'dev'
Requires-Dist: pytest>=8.0.0,<9 ; extra == 'dev'
Requires-Dist: sqlfluff>=2.3.2,<4 ; extra == 'dev'
Requires-Dist: fastapi~=0.115.14 ; extra == 'server'
Requires-Dist: uvicorn~=0.35.0 ; extra == 'server'
Requires-Dist: sqlfluff>=2.3.2,<4 ; extra == 'sqlfluff'
Requires-Dist: dbt-postgres~=1.8.0 ; extra == 'test'
Requires-Dist: dbt-core~=1.8.0 ; extra == 'test'
Requires-Dist: psycopg2-binary>=2.8,<3.0 ; extra == 'test'
Requires-Dist: sqlfluff>=2.3.2,<4 ; extra == 'test'
Requires-Python: >=3.10, <3.14
Project-URL: Changelog, https://github.com/z3z1ma/dbt-core-interface/releases
Project-URL: Documentation, https://dbt-core-interface.readthedocs.io
Project-URL: Homepage, https://github.com/z3z1ma/dbt-core-interface
Project-URL: Repository, https://github.com/z3z1ma/dbt-core-interface
Provides-Extra: dev
Provides-Extra: server
Provides-Extra: sqlfluff
Provides-Extra: test
